dragonfire/__init__.py
dragonfire/learn.py
dragonfire/nlplib.py
dragonfire/omniscient.py
dragonfire/timex.py
dragonfire/utilities.py
dragonfire/wam.py
dragonfire/yoda.py
dragonfire-0.9.4.dist-info/DESCRIPTION.rst
dragonfire-0.9.4.dist-info/METADATA
dragonfire-0.9.4.dist-info/RECORD
dragonfire-0.9.4.dist-info/WHEEL
dragonfire-0.9.4.dist-info/entry_points.txt
dragonfire-0.9.4.dist-info/metadata.json
dragonfire-0.9.4.dist-info/top_level.txt
