Metadata-Version: 2.0
Name: dragonfire
Version: 0.9.4
Summary: Dragonfire is an open source virtual assistant project for Ubuntu based Linux distributions
Home-page: https://github.com/mertyildiran/Dragonfire
Author: Mehmet Mert Yildiran
Author-email: mert.yildiran@bil.omu.edu.tr
License: MIT
Keywords: virtual assistant machine learining artifical intelligence chat bot
Platform: UNKNOWN
Classifier: Development Status :: 3 - Alpha
Classifier: Intended Audience :: Developers
Classifier: Topic :: Scientific/Engineering :: Human Machine Interfaces
Classifier: License :: OSI Approved :: MIT License
Classifier: Natural Language :: English
Classifier: Operating System :: POSIX :: Linux
Classifier: Programming Language :: Python :: 2.7
Requires-Dist: PyUserInput
Requires-Dist: SpeechRecognition
Requires-Dist: google-api-python-client
Requires-Dist: spacy
Requires-Dist: tinydb
Requires-Dist: wikipedia
Requires-Dist: youtube-dl
Provides-Extra: optionals
Requires-Dist: egenix-mx-base; extra == 'optionals'
Requires-Dist: httplib2 (>=0.9.1); extra == 'optionals'
Requires-Dist: lxml; extra == 'optionals'
Requires-Dist: nltk; extra == 'optionals'
Requires-Dist: pyaudio; extra == 'optionals'
